veto_sdk/__init__.py
veto_sdk/core.py
veto_sdk/errors.py
veto_sdk/types.py
veto_sdk-0.1.0.dist-info/METADATA
veto_sdk-0.1.0.dist-info/WHEEL
veto_sdk-0.1.0.dist-info/RECORD
