Metadata-Version: 2.4
Name: veto-sdk
Version: 0.1.0
Summary: A guardrail system for AI agent tool calls - Python SDK
Project-URL: Homepage, https://veto.run
Project-URL: Repository, https://github.com/VulnZap/veto
Project-URL: Documentation, https://github.com/VulnZap/veto/tree/master/packages/sdk-python
Author: Plaw, Inc.
License-Expression: Apache-2.0
Keywords: agent,ai,anthropic,guardrail,langchain,llm,openai,safety,tool-calls
Classifier: Development Status :: 3 - Alpha
Classifier: Intended Audience :: Developers
Classifier: License :: OSI Approved :: Apache Software License
Classifier: Programming Language :: Python :: 3
Classifier: Programming Language :: Python :: 3.9
Classifier: Programming Language :: Python :: 3.10
Classifier: Programming Language :: Python :: 3.11
Classifier: Programming Language :: Python :: 3.12
Classifier: Topic :: Scientific/Engineering :: Artificial Intelligence
Classifier: Topic :: Software Development :: Libraries :: Python Modules
Requires-Python: >=3.9
Requires-Dist: httpx>=0.25.0
Requires-Dist: pyyaml>=6.0
Provides-Extra: anthropic
Requires-Dist: anthropic>=0.18; extra == 'anthropic'
Provides-Extra: dev
Requires-Dist: mypy>=1.0; extra == 'dev'
Requires-Dist: pytest-asyncio>=0.21; extra == 'dev'
Requires-Dist: pytest-cov>=4.0; extra == 'dev'
Requires-Dist: pytest>=7.0; extra == 'dev'
Requires-Dist: ruff>=0.1.0; extra == 'dev'
Provides-Extra: langchain
Requires-Dist: langchain>=0.1; extra == 'langchain'
Provides-Extra: openai
Requires-Dist: openai>=1.0; extra == 'openai'
